{
  "parent": "minecraft:recipes/root",
  "criteria": {
    "has_corn": {
      "conditions": {
        "items": [
          {
            "items": [
              "shuckhorror:corn_1"
            ]
          }
        ]
      },
      "trigger": "minecraft:inventory_changed"
    },
    "has_the_recipe": {
      "conditions": {
        "recipe": "shuckhorror:corn_bread"
      },
      "trigger": "minecraft:recipe_unlocked"
    }
  },
  "requirements": [
    [
      "has_corn",
      "has_the_recipe"
    ]
  ],
  "rewards": {
    "recipes": [
      "shuckhorror:corn_bread"
    ]
  }
}